D_flip_flop/my_dff8.v
module my_dff8(
    input wire clk,
    input wire [7:0] d,
    output reg [7:0] q
);
    always @(posedge clk ) begin
        begin
            q <= d; 
        end
    end
endmodule

D_flip_flop/my_dff8_tb.v
`timescale 1ns/1ps
`include "my_dff8.v"

module my_dff8_tb;

    reg clk;
    reg [7:0] d;
    wire [7:0] q;

    my_dff8 uut (
        .clk(clk),
        .d(d),
        .q(q)
    );

    initial begin
        $dumpfile("my_dff8_tb.vcd");
        $dumpvars(0, my_dff8_tb);

        // Initialize clock
        clk = 0;
        forever #5 clk = ~clk; // Toggle clock every 5 ns
    end

    initial begin
        // Test case 1: Load value 8'b00000001
        d = 8'b00000001; #10;
        $display("d = %b, q = %b", d, q); // Expected: q = 00000001

        // Test case 2: Load value 8'b00000010
        d = 8'b00000010; #10;
        $display("d = %b, q = %b", d, q); // Expected: q = 00000010

        // Test case 3: Load value 8'b11111111
        d = 8'b11111111; #10;
        $display("d = %b, q = %b", d, q); // Expected: q = 11111111

        // Test case 4: Load value 8'b10101010
        d = 8'b10101010; #10;
        $display("d = %b, q = %b", d, q); // Expected: q = 10101010

        $finish;
    end
endmodule

D_flip_flop/my_dff8_tb.vcd
$date
	Sun Jun 15 09:42:25 2025
$end
$version
	Icarus Verilog
$end
$timescale
	1ps
$end
$scope module my_dff8_tb $end
$var wire 8 ! q [7:0] $end
$var reg 1 " clk $end
$var reg 8 # d [7:0] $end
$scope module uut $end
$var wire 1 " clk $end
$var wire 8 $ d [7:0] $end
$var reg 8 % q [7:0] $end
$upscope $end
$upscope $end
$enddefinitions $end
$comment Show the parameter values. $end
$dumpall
$end
#0
$dumpvars
bx %
b1 $
b1 #
0"
bx !
$end
#5000
b1 !
b1 %
1"
#10000
0"
b10 #
b10 $
#15000
b10 !
b10 %
1"
#20000
0"
b11111111 #
b11111111 $
#25000
b11111111 !
b11111111 %
1"
#30000
0"
b10101010 #
b10101010 $
#35000
b10101010 !
b10101010 %
1"
